django_priority_batch/__about__.py
django_priority_batch/__init__.py
django_priority_batch/middleware.py
django_priority_batch/prioritized_batcher.py
django_priority_batch-4.0.0.dist-info/LICENSE
django_priority_batch-4.0.0.dist-info/METADATA
django_priority_batch-4.0.0.dist-info/WHEEL
django_priority_batch-4.0.0.dist-info/top_level.txt
django_priority_batch-4.0.0.dist-info/RECORD
