Metadata-Version: 2.1
Name: django-priority-batch
Version: 4.0.0
Summary: TODO.
Home-page: https://github.com/genialis/django-priority-batch
Author: Genialis, Inc.
Author-email: dev-team@genialis.com
License: Apache License (2.0)
Keywords: django transaction batching prioritization
Platform: UNKNOWN
Classifier: Development Status :: 4 - Beta
Classifier: Framework :: Django
Classifier: Intended Audience :: Developers
Classifier: Topic :: Software Development :: Libraries :: Application Frameworks
Classifier: Topic :: Software Development :: Libraries :: Python Modules
Classifier: License :: OSI Approved :: Apache Software License
Classifier: Operating System :: OS Independent
Classifier: Programming Language :: Python
Classifier: Programming Language :: Python :: 3
Classifier: Programming Language :: Python :: 3.6
Classifier: Programming Language :: Python :: 3.7
Classifier: Programming Language :: Python :: 3.8
Classifier: Programming Language :: Python :: 3.9
Classifier: Programming Language :: Python :: 3.10
Requires-Python: >=3.6, <3.11
License-File: LICENSE
Requires-Dist: Django (~=3.2)
Provides-Extra: docs
Requires-Dist: Sphinx ; extra == 'docs'
Requires-Dist: sphinx-rtd-theme ; extra == 'docs'
Provides-Extra: package
Requires-Dist: twine ; extra == 'package'
Requires-Dist: wheel ; extra == 'package'
Provides-Extra: test
Requires-Dist: black ; extra == 'test'
Requires-Dist: pydocstyle ; extra == 'test'
Requires-Dist: check-manifest ; extra == 'test'
Requires-Dist: readme-renderer ; extra == 'test'
Requires-Dist: setuptools-scm ; extra == 'test'
Requires-Dist: setuptools (>=59.6.0) ; extra == 'test'
Requires-Dist: pytest ; extra == 'test'
Requires-Dist: pytest-django ; extra == 'test'
